{
  "result": "success",
  "cursor": "3bb670b6-3bb670b6-5f75993d",
  "count": 100,
  "transactions": [
    {
      "blockchain": "ethereum",
      "symbol": "usdt",
      "id": "1001746759",
      "transaction_type": "transfer",
      "hash": "e656373999f33ddc6a42828a62c1be9f88d26bc833614732aa72319bd9aa63a0",
      "from": {
        "address": "aaf5959918b74a6cab04a18987ab73dd9567a8d1",
        "owner_type": "unknown"
      },
      "to": {
        "address": "343d44192ec0c87a8aee8fe45e7419ec27dfac05",
        "owner_type": "unknown"
      },
      "timestamp": 1601540680,
      "amount": 2505848,
      "amount_usd": 2519764.2,
      "transaction_count": 1
    },
    {
      "blockchain": "ethereum",
      "symbol": "eth",
      "id": "1001747000",
      "transaction_type": "transfer",
      "hash": "bb37a05b1221389582f7d23853b08df27d2191c0c3f93a2d46118c86c7ab760b",
      "from": {
        "address": "36cc7b13029b5dee4034745fb4f24034f3f2ffc6",
        "owner_type": "unknown"
      },
      "to": {
        "address": "c02aaa39b223fe8d0a0e5c4f27ead9083c756cc2",
        "owner": "wrapped ether",
        "owner_type": "other"
      },
      "timestamp": 1601540687,
      "amount": 1447,
      "amount_usd": 526244.6,
      "transaction_count": 1
    },
    {
      "blockchain": "ethereum",
      "symbol": "usdt",
      "id": "1001747485",
      "transaction_type": "transfer",
      "hash": "6289f35402adb8e5df54048c93637f352ae651492461bab92ee7de62cd663138",
      "from": {
        "address": "876eabf441b2ee5b5b0554fd502a8e0600950cfa",
        "owner": "bitfinex",
        "owner_type": "exchange"
      },
      "to": {
        "address": "2db8a54c3d3b16146efaf7b9a776d94e259c8d80",
        "owner": "binance",
        "owner_type": "exchange"
      },
      "timestamp": 1601540689,
      "amount": 500000,
      "amount_usd": 500372.03,
      "transaction_count": 1
    },
    {
      "blockchain": "ethereum",
      "symbol": "usdt",
      "id": "1001749758",
      "transaction_type": "transfer",
      "hash": "ae9cd890b3353ff46156975797338c350f388f77761c848147b39725831d08f6",
      "from": {
        "address": "77fdd5c90e3f50f22eeabd87565395920a1b103d",
        "owner_type": "unknown"
      },
      "to": {
        "address": "23f3bfdc3638a957098654c312cd788cfa2adf37",
        "owner_type": "unknown"
      },
      "timestamp": 1601540834,
      "amount": 1499999.5,
      "amount_usd": 1498937.5,
      "transaction_count": 1
    },
    {
      "blockchain": "ethereum",
      "symbol": "eth",
      "id": "1001752329",
      "transaction_type": "transfer",
      "hash": "772e905af1dc13460147c60f8cfcc2d8fdeb98ae7d6728f41c22581160bf2b84",
      "from": {
        "address": "63c81b5c9db704d3be56a0e4b7b6e262208441e6",
        "owner_type": "unknown"
      },
      "to": {
        "address": "88a7b02542d71f194e89d450f60954a9984ab8db",
        "owner_type": "unknown"
      },
      "timestamp": 1601541019,
      "amount": 1459.1257,
      "amount_usd": 533893.06,
      "transaction_count": 1
    },
    {
      "blockchain": "ethereum",
      "symbol": "usdc",
      "id": "1001752577",
      "transaction_type": "transfer",
      "hash": "92d10224e172cae47758c3e3c98fd9ec13d80fd53b5681492de5556dd89fedb5",
      "from": {
        "address": "f05e2a70346560d3228c7002194bb7c5dc8fe100",
        "owner": "binance",
        "owner_type": "exchange"
      },
      "to": {
        "address": "3f5ce5fbfe3e9af3971dd833d26ba9b5c936f0be",
        "owner": "binance",
        "owner_type": "exchange"
      },
      "timestamp": 1601541038,
      "amount": 1999999,
      "amount_usd": 1999999,
      "transaction_count": 1
    },
    {
      "blockchain": "ethereum",
      "symbol": "usdt",
      "id": "1001752681",
      "transaction_type": "transfer",
      "hash": "ccc7fa1ae63a6dc345dd51e3807f4c4e30daf4047305c3b4433d5f35e3029793",
      "from": {
        "address": "2db8a54c3d3b16146efaf7b9a776d94e259c8d80",
        "owner": "binance",
        "owner_type": "exchange"
      },
      "to": {
        "address": "3f5ce5fbfe3e9af3971dd833d26ba9b5c936f0be",
        "owner": "binance",
        "owner_type": "exchange"
      },
      "timestamp": 1601541038,
      "amount": 500000,
      "amount_usd": 500397.78,
      "transaction_count": 1
    },
    {
      "blockchain": "ethereum",
      "symbol": "eth",
      "id": "1001753470",
      "transaction_type": "transfer",
      "hash": "b8384c32a9685e6050d34c03f54452b50f284020cc8bdc3f8ccef1cde49df060",
      "from": {
        "address": "88a7b02542d71f194e89d450f60954a9984ab8db",
        "owner_type": "unknown"
      },
      "to": {
        "address": "9d50bcf873e310d533c65319ebdefecab7332d40",
        "owner_type": "unknown"
      },
      "timestamp": 1601541043,
      "amount": 1459.124,
      "amount_usd": 533892.44,
      "transaction_count": 1
    },
    {
      "blockchain": "tron",
      "symbol": "usdt",
      "id": "1001752838",
      "transaction_type": "transfer",
      "hash": "9bfb545385d1f8e166dcc6a6d13ad96f3eab314119d6a3311cc734a08fd90e6d",
      "from": {
        "address": "TW5VRTp1EjXAHULVFuvjC1mR4ixuALPooo",
        "owner_type": "unknown"
      },
      "to": {
        "address": "TPtuTt4pPPtTrsZYKibjfaSKN6oCkPbWep",
        "owner_type": "unknown"
      },
      "timestamp": 1601541117,
      "amount": 960000,
      "amount_usd": 960763.75,
      "transaction_count": 1
    },
    {
      "blockchain": "ethereum",
      "symbol": "usdt",
      "id": "1001756025",
      "transaction_type": "transfer",
      "hash": "efaa253a3d18dd85c2c5a966e0d36429bb218fae0ab3d5123ae2b330f9f3928b",
      "from": {
        "address": "e4fd147114df1939bc586678b9b2573327b2ba9e",
        "owner_type": "unknown"
      },
      "to": {
        "address": "0eb4cb2a0a9f40fdb48262c74d343c0ac01ad682",
        "owner_type": "unknown"
      },
      "timestamp": 1601541142,
      "amount": 887342,
      "amount_usd": 885020.4,
      "transaction_count": 1
    },
    {
      "blockchain": "tron",
      "symbol": "usdt",
      "id": "1001755526",
      "transaction_type": "transfer",
      "hash": "366b5a5c2bbfb1784229d6971ce163c96a24fc03dbd450f0af137737a5c97cfc",
      "from": {
        "address": "TPtuTt4pPPtTrsZYKibjfaSKN6oCkPbWep",
        "owner_type": "unknown"
      },
      "to": {
        "address": "TNaRAoLUyYEV2uF7GUrzSjRQTU8v5ZJ5VR",
        "owner": "huobi",
        "owner_type": "exchange"
      },
      "timestamp": 1601541195,
      "amount": 960000,
      "amount_usd": 963351.06,
      "transaction_count": 1
    },
    {
      "blockchain": "ethereum",
      "symbol": "storj",
      "id": "1001757961",
      "transaction_type": "transfer",
      "hash": "24ac779528422d5d6d2431a572dd5bde307dcac4cd986d73382f51b4db8a2890",
      "from": {
        "address": "3f5ce5fbfe3e9af3971dd833d26ba9b5c936f0be",
        "owner": "binance",
        "owner_type": "exchange"
      },
      "to": {
        "address": "63a27fa8a70097d43e333eaa4a2333e187a45361",
        "owner_type": "unknown"
      },
      "timestamp": 1601541306,
      "amount": 2099988.8,
      "amount_usd": 1058277.4,
      "transaction_count": 1
    },
    {
      "blockchain": "ethereum",
      "symbol": "usdt",
      "id": "1001759812",
      "transaction_type": "transfer",
      "hash": "e3ffdbeb2ac9cc440f04ab1f3d5c363f8e6521b415ee6a74f73242a61daf075f",
      "from": {
        "address": "69ee999d3b1580d30a871ea34864cce1ca664b25",
        "owner_type": "unknown"
      },
      "to": {
        "address": "593363555b5e09e46c65c6bb6bb827f2178739f3",
        "owner_type": "unknown"
      },
      "timestamp": 1601541356,
      "amount": 500000,
      "amount_usd": 501060.6,
      "transaction_count": 1
    },
    {
      "blockchain": "ethereum",
      "symbol": "eth",
      "id": "1001760088",
      "transaction_type": "transfer",
      "hash": "2eb5978c862ca2dea75006d39591864cdbc7589b0441caba9768993ae9e1d4a6",
      "from": {
        "address": "f66852bc122fd40bfecc63cd48217e88bda12109",
        "owner": "huobi",
        "owner_type": "exchange"
      },
      "to": {
        "address": "4faa508925950a7291c91fbfe0ffd495acfdd86f",
        "owner_type": "unknown"
      },
      "timestamp": 1601541382,
      "amount": 1369.993,
      "amount_usd": 504198.5,
      "transaction_count": 1
    },
    {
      "blockchain": "ethereum",
      "symbol": "usdt",
      "id": "1001775012",
      "transaction_type": "transfer",
      "hash": "c5b31287029d9f6bb54252690e2dfe9e786ccd5062d18c5a64cd5be6dd231df2",
      "from": {
        "address": "0681d8db095565fe8a346fa0277bffde9c0edbbf",
        "owner": "binance",
        "owner_type": "exchange"
      },
      "to": {
        "address": "7fd82ed5c6665f6242276a27a8f4fe4c27531673",
        "owner_type": "unknown"
      },
      "timestamp": 1601541397,
      "amount": 499996,
      "amount_usd": 502894.38,
      "transaction_count": 1
    },
    {
      "blockchain": "bitcoin",
      "symbol": "btc",
      "id": "1001760429",
      "transaction_type": "transfer",
      "hash": "a831d66c20376576df3b9e74d2a2e4307615ff6cd4a429053f68e68511920d46",
      "from": {
        "address": "bc1qv244n7sz322uyg9vywltq6jgspxm8dh8xkq2dwl9qfzc4v6mmr9sm20msj",
        "owner_type": "unknown"
      },
      "to": {
        "address": "bc1q8u4px4jzay8c8nnvvynkhmsqludxltkw5k7dzqpvmvkzl6naps8q32luvs",
        "owner_type": "unknown"
      },
      "timestamp": 1601541413,
      "amount": 76.71241,
      "amount_usd": 833596.56,
      "transaction_count": 1
    },
    {
      "blockchain": "bitcoin",
      "symbol": "btc",
      "id": "1001760477",
      "transaction_type": "transfer",
      "hash": "d554722eb3e95cfa4ba4a22c8704f0b05d3dbef6ccde3ead49fabb96d25b8ff9",
      "from": {
        "address": "3PNWakFY3vRG2mYyVcy6qMgJwPKgNNkP74",
        "owner_type": "unknown"
      },
      "to": {
        "address": "3Mi9GtCTW465nmwduwPr9sBV4aS8RcBZTV",
        "owner_type": "unknown"
      },
      "timestamp": 1601541413,
      "amount": 49.557995,
      "amount_usd": 538522.7,
      "transaction_count": 1
    },
    {
      "blockchain": "bitcoin",
      "symbol": "btc",
      "id": "1001760715",
      "transaction_type": "transfer",
      "hash": "796d50edb8b4c72697c772a860e907fb01bb30801547ca0e6d38a2e3e27f7cea",
      "from": {
        "address": "bc1q8h67dytup75uurg9jpj32mtudrauraf2fd7lnp",
        "owner_type": "unknown"
      },
      "to": {
        "address": "bc1qrt4lhky8y4vc3a8qh9tkml8dhlr66unscslpjf",
        "owner_type": "unknown"
      },
      "timestamp": 1601541413,
      "amount": 166.69136,
      "amount_usd": 1811354.2,
      "transaction_count": 1
    },
    {
      "blockchain": "bitcoin",
      "symbol": "btc",
      "id": "1001760717",
      "transaction_type": "transfer",
      "hash": "fba711a5be29454102e2f531338061ebb40add32afe1767d8f131239f1d23a95",
      "from": {
        "address": "bc1qrt4lhky8y4vc3a8qh9tkml8dhlr66unscslpjf",
        "owner_type": "unknown"
      },
      "to": {
        "address": "bc1qxv9vek0xts9ktv0l06a6stsx404cps9n4dsew8",
        "owner_type": "unknown"
      },
      "timestamp": 1601541413,
      "amount": 164.41043,
      "amount_usd": 1786568.5,
      "transaction_count": 1
    },
    {
      "blockchain": "bitcoin",
      "symbol": "btc",
      "id": "1001760722",
      "transaction_type": "transfer",
      "hash": "cdeb84af4fc88f8c38718988e1bf50f8b689ba91e5f82365201efbc04c058f87",
      "from": {
        "address": "bc1qxv9vek0xts9ktv0l06a6stsx404cps9n4dsew8",
        "owner_type": "unknown"
      },
      "to": {
        "address": "bc1qstpzhd7ydxd8qx007yyazgahww3zju6s7y4ere",
        "owner_type": "unknown"
      },
      "timestamp": 1601541413,
      "amount": 162.69785,
      "amount_usd": 1767958.6,
      "transaction_count": 1
    },
    {
      "blockchain": "bitcoin",
      "symbol": "btc",
      "id": "1001761432",
      "transaction_type": "transfer",
      "hash": "efdc1793513fb4b4a82eb8dd8c25eb34a4c92a1f99ef0f3397d3ef1a48c09b36",
      "from": {
        "address": "Multiple Addresses",
        "owner": "binance",
        "owner_type": "exchange"
      },
      "to": {
        "address": "1NYAd6fA2dc5xowuweFUSDRqRTEzDwk28",
        "owner": "okex",
        "owner_type": "exchange"
      },
      "timestamp": 1601541413,
      "amount": 62,
      "amount_usd": 673723.94,
      "transaction_count": 1
    },
    {
      "blockchain": "bitcoin",
      "symbol": "btc",
      "id": "1001761780",
      "transaction_type": "transfer",
      "hash": "2177705d2230d0dc8f544098216bb700e57a19824bf10b059c0b005be36da091",
      "from": {
        "address": "3GAKvJmsPukxUdeN1cgzw66PyYQ8fqcU1m",
        "owner_type": "unknown"
      },
      "to": {
        "address": "32JbQxtn5i7Xrb4E4AkudLG8MtCwimyyt6",
        "owner_type": "unknown"
      },
      "timestamp": 1601541413,
      "amount": 58.439487,
      "amount_usd": 635033.56,
      "transaction_count": 1
    },
    {
      "blockchain": "bitcoin",
      "symbol": "btc",
      "id": "1001762205",
      "transaction_type": "transfer",
      "hash": "5818dddda26946caccb6b5220fc6d3b539b2222a71aadbfda40079a8ca4ebf40",
      "from": {
        "address": "1NDyJtNTjmwk5xPNhjgAMu4HDHigtobu1s",
        "owner": "binance",
        "owner_type": "exchange"
      },
      "to": {
        "address": "15UGVZhgfhr7PozC45Fp9JA82QsR3Tefj8",
        "owner_type": "unknown"
      },
      "timestamp": 1601541413,
      "amount": 78.99,
      "amount_usd": 858346.06,
      "transaction_count": 1
    },
    {
      "blockchain": "bitcoin",
      "symbol": "btc",
      "id": "1001762481",
      "transaction_type": "transfer",
      "hash": "d485309605170cf9726e6f914ba0262f7dbd090eedc883dcc1ded61441ca3ff4",
      "from": {
        "address": "Multiple Addresses",
        "owner_type": "unknown"
      },
      "to": {
        "address": "1PCkFoQZMqcuRubfwbnP4Zhid9GDfvEKM8",
        "owner": "coinbase",
        "owner_type": "exchange"
      },
      "timestamp": 1601541413,
      "amount": 80.81011,
      "amount_usd": 878124.3,
      "transaction_count": 1
    },
    {
      "blockchain": "bitcoin",
      "symbol": "btc",
      "id": "1001764707",
      "transaction_type": "transfer",
      "hash": "1b2821d93c5e7fec1369e3ccad4defd2c9df69efa3d9948625eb721a1586217b",
      "from": {
        "address": "38D278dV8a4TVrt896NAh2rKAL8r2VCtrn",
        "owner_type": "unknown"
      },
      "to": {
        "address": "3ET4AfdRug8ANzjhhWcxDdSYaih7UAan7j",
        "owner_type": "unknown"
      },
      "timestamp": 1601541413,
      "amount": 121.026596,
      "amount_usd": 1315137.4,
      "transaction_count": 1
    },
    {
      "blockchain": "bitcoin",
      "symbol": "btc",
      "id": "1001764708",
      "transaction_type": "transfer",
      "hash": "1b2821d93c5e7fec1369e3ccad4defd2c9df69efa3d9948625eb721a1586217b",
      "from": {
        "address": "38D278dV8a4TVrt896NAh2rKAL8r2VCtrn",
        "owner_type": "unknown"
      },
      "to": {
        "address": "31jKj2i8UCQw6HAxAEFidktsCPxZDxWJYc",
        "owner": "binance",
        "owner_type": "exchange"
      },
      "timestamp": 1601541413,
      "amount": 62.091,
      "amount_usd": 674712.8,
      "transaction_count": 1
    },
    {
      "blockchain": "bitcoin",
      "symbol": "btc",
      "id": "1001764808",
      "transaction_type": "transfer",
      "hash": "f8630a9192693175f4b02b660e57b1e3bc683ac9d0750b380e2d9def9054e128",
      "from": {
        "address": "3NY2StzxqkLn9JCSsNSsZAx6hsiR7SEisJ",
        "owner_type": "unknown"
      },
      "to": {
        "address": "3HCJuLa5F4hSxTE3xab7KAcuLDKH6A3ULx",
        "owner_type": "unknown"
      },
      "timestamp": 1601541413,
      "amount": 144.11598,
      "amount_usd": 1566038.5,
      "transaction_count": 1
    },
    {
      "blockchain": "bitcoin",
      "symbol": "btc",
      "id": "1001769187",
      "transaction_type": "transfer",
      "hash": "1f124ad74e3c7032d0c5dd2a7e2706d812a7f15f244fb72759e6d7d8b3dbb122",
      "from": {
        "address": "bc1q8z3resxms0dv673zyytwj46qyk66upsa6uh9y7e8aaq297fdchsq8qmlvp",
        "owner_type": "unknown"
      },
      "to": {
        "address": "bc1qqplh0epupan36z3zf0t030yk2dwka7rnv2cl30xsyrypurfq87psqs2t4j",
        "owner_type": "unknown"
      },
      "timestamp": 1601541413,
      "amount": 128.008,
      "amount_usd": 1391000.8,
      "transaction_count": 1
    },
    {
      "blockchain": "bitcoin",
      "symbol": "btc",
      "id": "1001769189",
      "transaction_type": "transfer",
      "hash": "368452db269a2b867d5bd4217a62689ee17cd11a58a53b2f1a009a7d16fbe028",
      "from": {
        "address": "bc1qwj2ne2xu9t5tue88w4u0lpxhr2exqmrvhh3glzt4xusppnhqdtestqnyf6",
        "owner_type": "unknown"
      },
      "to": {
        "address": "bc1q6gx2gl32xarzkkvm0ansa93c7zwtndf4pk7cm35qewj03h762kdsd3qrkw",
        "owner_type": "unknown"
      },
      "timestamp": 1601541413,
      "amount": 101.06828,
      "amount_usd": 1098260,
      "transaction_count": 1
    },
    {
      "blockchain": "bitcoin",
      "symbol": "btc",
      "id": "1001769251",
      "transaction_type": "transfer",
      "hash": "bfc62fd2bdeef47e0121609fc98acd9a35344654646ff8b73e5b245adebcbc20",
      "from": {
        "address": "1N52wHoVR79PMDishab2XmRHsbekCdGquK",
        "owner": "bittrex",
        "owner_type": "exchange"
      },
      "to": {
        "address": "39dY6SZze3pvFZ7NV2oDKABUGFygrt3db9",
        "owner_type": "unknown"
      },
      "timestamp": 1601541413,
      "amount": 74.9985,
      "amount_usd": 814972.3,
      "transaction_count": 1
    },
    {
      "blockchain": "bitcoin",
      "symbol": "btc",
      "id": "1001769670",
      "transaction_type": "transfer",
      "hash": "e73a423149d3fa63bbd0ae2e36a16f1b7e8f987ad832650e1071fd71841d9aa5",
      "from": {
        "address": "Multiple Addresses",
        "owner": "okex",
        "owner_type": "exchange"
      },
      "to": {
        "address": "1XYZJsM6cnyuDMVnfFufb8dzVM7cS5rqd",
        "owner": "bitflyer",
        "owner_type": "exchange"
      },
      "timestamp": 1601541413,
      "amount": 378,
      "amount_usd": 4107542.8,
      "transaction_count": 1
    },
    {
      "blockchain": "bitcoin",
      "symbol": "btc",
      "id": "1001771332",
      "transaction_type": "transfer",
      "hash": "913c082f8f20be58e8c8aec09a4601bea762d78d5923c3cfbb801bee8837aebc",
      "from": {
        "address": "39fPC8ND8442NxYNwfU1JBLvKjPcUxjGH1",
        "owner_type": "unknown"
      },
      "to": {
        "address": "38yAWmdUYw5YV1TPrhYbXZpSBPjoPtBUxe",
        "owner_type": "unknown"
      },
      "timestamp": 1601541413,
      "amount": 53.53653,
      "amount_usd": 581755.5,
      "transaction_count": 1
    },
    {
      "blockchain": "bitcoin",
      "symbol": "btc",
      "id": "1001771567",
      "transaction_type": "transfer",
      "hash": "004bd113913e45ba462ca6441e5fc73a3481578354f0b8bcf7ae9d630cd549c2",
      "from": {
        "address": "Multiple Addresses",
        "owner_type": "unknown"
      },
      "to": {
        "address": "1HuvmCBh4CVwvtXQQECk51LV89wZdQaraj",
        "owner": "okex",
        "owner_type": "exchange"
      },
      "timestamp": 1601541413,
      "amount": 91,
      "amount_usd": 988852.9,
      "transaction_count": 1
    },
    {
      "blockchain": "bitcoin",
      "symbol": "btc",
      "id": "1001771574",
      "transaction_type": "transfer",
      "hash": "b5934382999503d88f52984feca9cbe48cd0c3098cc7ad148299e6ec4eb2201a",
      "from": {
        "address": "Multiple Addresses",
        "owner_type": "unknown"
      },
      "to": {
        "address": "bc1q9362tjaae28th06rddn0j99qevmgamasxcfpry",
        "owner_type": "unknown"
      },
      "timestamp": 1601541413,
      "amount": 115,
      "amount_usd": 1249649.2,
      "transaction_count": 1
    },
    {
      "blockchain": "bitcoin",
      "symbol": "btc",
      "id": "1001773392",
      "transaction_type": "transfer",
      "hash": "84ae73063e5a8f8f72f4f8609c520dff8ac8de6b26f652430bf37ef3ceadf913",
      "from": {
        "address": "1AEgdWjJrEbroURgWmPrXkFdzxGxdF7c4G",
        "owner_type": "unknown"
      },
      "to": {
        "address": "1HGYwg2BY5Z1YHkpLHH3d7pTjM9pFakZhJ",
        "owner_type": "unknown"
      },
      "timestamp": 1601541413,
      "amount": 75.41189,
      "amount_usd": 819464.44,
      "transaction_count": 1
    },
    {
      "blockchain": "bitcoin",
      "symbol": "btc",
      "id": "1001773691",
      "transaction_type": "transfer",
      "hash": "7ec0785b86bca902fd046ed5b06256ea7d15155d55f598503ff1c452cdbd5ec2",
      "from": {
        "address": "1FtzFbeHkKotFYU9yuLKZmch86yKmRHLQN",
        "owner_type": "unknown"
      },
      "to": {
        "address": "17i3TWjz8TgW3j26kqcpjLECNsYoPPytpf",
        "owner_type": "unknown"
      },
      "timestamp": 1601541413,
      "amount": 176.7322,
      "amount_usd": 1920463.1,
      "transaction_count": 1
    },
    {
      "blockchain": "ethereum",
      "symbol": "eth",
      "id": "1001775498",
      "transaction_type": "transfer",
      "hash": "f240e413ce6906b4738b5a5aa7e475e0b5099085bb0af58c032c6bf07e067bd5",
      "from": {
        "address": "7329e4350d7381c6203bfb37f531230108ac3fa0",
        "owner_type": "unknown"
      },
      "to": {
        "address": "5c6fc02d24c20c86c94a28dbae8f7fd27db04399",
        "owner_type": "unknown"
      },
      "timestamp": 1601541436,
      "amount": 5536.12,
      "amount_usd": 2022505.2,
      "transaction_count": 1
    },
    {
      "blockchain": "ethereum",
      "symbol": "usdt",
      "id": "1001781543",
      "transaction_type": "transfer",
      "hash": "724e0cc3021035dd5f35741a819afa14b34ba20942c2b5edbbbdb20b1045d327",
      "from": {
        "address": "ab9fe062c4acdb57d9e04d433e485e0fb9aba4f5",
        "owner": "huobi",
        "owner_type": "exchange"
      },
      "to": {
        "address": "6748f50f686bfbca6fe8ad62b22228b87f31ff2b",
        "owner": "huobi",
        "owner_type": "exchange"
      },
      "timestamp": 1601541447,
      "amount": 500000,
      "amount_usd": 503674.25,
      "transaction_count": 1
    },
    {
      "blockchain": "ethereum",
      "symbol": "eth",
      "id": "1001782021",
      "transaction_type": "transfer",
      "hash": "953c47669a2f3553b6b842d80bcbcca6ff41e99f8e4741e8c9301e06962ffec2",
      "from": {
        "address": "9d50bcf873e310d533c65319ebdefecab7332d40",
        "owner_type": "unknown"
      },
      "to": {
        "address": "7a250d5630b4cf539739df2c5dacb4c659f2488d",
        "owner": "uniswap",
        "owner_type": "other"
      },
      "timestamp": 1601541484,
      "amount": 1450,
      "amount_usd": 530290.9,
      "transaction_count": 1
    },
    {
      "blockchain": "ethereum",
      "symbol": "eth",
      "id": "1001782875",
      "transaction_type": "transfer",
      "hash": "203a630674d2f950b902c9125e24e3d22bc94fa798744dbfe4670a4f9052baf1",
      "from": {
        "address": "ee2826453a4fd5afeb7ceffeef3ffa2320081268",
        "owner_type": "unknown"
      },
      "to": {
        "address": "398ec7346dcd622edc5ae82352f02be94c62d119",
        "owner_type": "unknown"
      },
      "timestamp": 1601541518,
      "amount": 1720,
      "amount_usd": 629034.75,
      "transaction_count": 1
    },
    {
      "blockchain": "ethereum",
      "symbol": "usdt",
      "id": "1001782933",
      "transaction_type": "transfer",
      "hash": "95055af1192590d464091eb868685d9727308cc99da812311d9196bd5c6f6969",
      "from": {
        "address": "ee9156c93ebb836513968f92b4a67721f3cea08a",
        "owner_type": "unknown"
      },
      "to": {
        "address": "a75cd63034c3fbbaef11ab7a80bf17bc4e21291d",
        "owner_type": "unknown"
      },
      "timestamp": 1601541518,
      "amount": 1560868,
      "amount_usd": 1570302.5,
      "transaction_count": 1
    },
    {
      "blockchain": "bitcoin",
      "symbol": "btc",
      "id": "1001775637",
      "transaction_type": "transfer",
      "hash": "db182c90443dcbdfc597866bdfeab36cea2d6e1265a89f8920b6953160f973c1",
      "from": {
        "address": "bc1q8u4px4jzay8c8nnvvynkhmsqludxltkw5k7dzqpvmvkzl6naps8q32luvs",
        "owner_type": "unknown"
      },
      "to": {
        "address": "bc1qsgrtufufpx0dhzyzmj57ryfa0e0ckur4t7g3zx0efe250zwkugvqheuf6l",
        "owner_type": "unknown"
      },
      "timestamp": 1601541534,
      "amount": 75.13961,
      "amount_usd": 820841.9,
      "transaction_count": 1
    },
    {
      "blockchain": "bitcoin",
      "symbol": "btc",
      "id": "1001775655",
      "transaction_type": "transfer",
      "hash": "917169cfd59974df7706df5a1f0939eb4efceda144a1478bcb2f782b62e7186d",
      "from": {
        "address": "bc1qstpzhd7ydxd8qx007yyazgahww3zju6s7y4ere",
        "owner_type": "unknown"
      },
      "to": {
        "address": "bc1qrt4lhky8y4vc3a8qh9tkml8dhlr66unscslpjf",
        "owner_type": "unknown"
      },
      "timestamp": 1601541534,
      "amount": 161.58928,
      "amount_usd": 1765237.5,
      "transaction_count": 1
    },
    {
      "blockchain": "bitcoin",
      "symbol": "btc",
      "id": "1001775691",
      "transaction_type": "transfer",
      "hash": "1503b547252bf967f42454dae8efd3e2b230d8adaef96fdfc1c7222af81b89ca",
      "from": {
        "address": "bc1qq2lyv0wvqv6833qvssdffa9wz2rj06y9pmdvqt",
        "owner_type": "unknown"
      },
      "to": {
        "address": "3Pp78k1rLtanahSXkDPfJ4yeBEAPAXqyLE",
        "owner_type": "unknown"
      },
      "timestamp": 1601541534,
      "amount": 58.159866,
      "amount_usd": 635351.44,
      "transaction_count": 1
    },
    {
      "blockchain": "bitcoin",
      "symbol": "btc",
      "id": "1001775782",
      "transaction_type": "transfer",
      "hash": "78f2182d87506e57f7690222d31d81b714b92228353bec3d7e605cd40fb3f914",
      "from": {
        "address": "Multiple Addresses",
        "owner_type": "unknown"
      },
      "to": {
        "address": "33zU1yGK8DGfp4aprxHDAxZUzw1ULtrEtx",
        "owner_type": "unknown"
      },
      "timestamp": 1601541534,
      "amount": 606.0103,
      "amount_usd": 6620192,
      "transaction_count": 1
    },
    {
      "blockchain": "bitcoin",
      "symbol": "btc",
      "id": "1001775783",
      "transaction_type": "transfer",
      "hash": "78f2182d87506e57f7690222d31d81b714b92228353bec3d7e605cd40fb3f914",
      "from": {
        "address": "Multiple Addresses",
        "owner_type": "unknown"
      },
      "to": {
        "address": "3JcsCDePGX85cLS9vAYTCCn9ZLPpQZueWu",
        "owner": "okex",
        "owner_type": "exchange"
      },
      "timestamp": 1601541534,
      "amount": 150,
      "amount_usd": 1638633.5,
      "transaction_count": 1
    },
    {
      "blockchain": "bitcoin",
      "symbol": "btc",
      "id": "1001776156",
      "transaction_type": "transfer",
      "hash": "c01acd073448bee38fa490ac606a3b505ed10df8dd202510fae848574c046802",
      "from": {
        "address": "bc1qpdk6g5glkp6yj2cut7940zl5t70j5rr32xjsd29qnreed0pq6w9qqna2a9",
        "owner_type": "unknown"
      },
      "to": {
        "address": "bc1q7hyu9svk7yknevq2el5zfpsvweep7wgc4h7q9f7czlamfxtuu73stafzpg",
        "owner_type": "unknown"
      },
      "timestamp": 1601541534,
      "amount": 241.5312,
      "amount_usd": 2638541,
      "transaction_count": 1
    },
    {
      "blockchain": "bitcoin",
      "symbol": "btc",
      "id": "1001776231",
      "transaction_type": "transfer",
      "hash": "3f25825505ea0dde516954901e9b6433e61d6f6ce6b754c31a22ba47f19f6be1",
      "from": {
        "address": "bc1qqplh0epupan36z3zf0t030yk2dwka7rnv2cl30xsyrypurfq87psqs2t4j",
        "owner_type": "unknown"
      },
      "to": {
        "address": "bc1qk4kq8tsf5ezd9js72xfcp7qrqeg0002leu79zcjt24449yn860dqcfml45",
        "owner_type": "unknown"
      },
      "timestamp": 1601541534,
      "amount": 127.994125,
      "amount_usd": 1398236.4,
      "transaction_count": 1
    },
    {
      "blockchain": "bitcoin",
      "symbol": "btc",
      "id": "1001776391",
      "transaction_type": "transfer",
      "hash": "e954aea7bdc22ec22c1ffa5b6e14088b258d3272d0253c9d34d87933bccabd45",
      "from": {
        "address": "1KNh9FQdeaBRzPEvPqzoUbFabSt3v6eTZT",
        "owner_type": "unknown"
      },
      "to": {
        "address": "1LY1EKwGLTdShWJASTgPxnabqwUq6dusbn",
        "owner_type": "unknown"
      },
      "timestamp": 1601541534,
      "amount": 58.010082,
      "amount_usd": 633715.1,
      "transaction_count": 1
    },
    {
      "blockchain": "bitcoin",
      "symbol": "btc",
      "id": "1001777502",
      "transaction_type": "transfer",
      "hash": "28ba5c6aaea4b245dbf31e2079c403ec74656b5096a469bd832dad1eda2887f8",
      "from": {
        "address": "Multiple Addresses",
        "owner_type": "unknown"
      },
      "to": {
        "address": "bc1q3fqssuzjzuc3hs2f02k752rtnuzsca3y6r2hl2",
        "owner_type": "unknown"
      },
      "timestamp": 1601541534,
      "amount": 75.544556,
      "amount_usd": 825265.6,
      "transaction_count": 1
    },
    {
      "blockchain": "bitcoin",
      "symbol": "btc",
      "id": "1001777932",
      "transaction_type": "transfer",
      "hash": "d97b4fee957bdc6c6d7a5ae678d33e045f10d6fea2877509ce4c3f707d02cd46",
      "from": {
        "address": "Multiple Addresses",
        "owner_type": "unknown"
      },
      "to": {
        "address": "bc1q9362tjaae28th06rddn0j99qevmgamasxcfpry",
        "owner_type": "unknown"
      },
      "timestamp": 1601541534,
      "amount": 108.7922,
      "amount_usd": 1188470.2,
      "transaction_count": 1
    },
    {
      "blockchain": "bitcoin",
      "symbol": "btc",
      "id": "1001779033",
      "transaction_type": "transfer",
      "hash": "2a44a1b4f79d41397b2ffedf514aaeaeacf02c073d80d344ff028493d1f20ffb",
      "from": {
        "address": "3LtHACy6WPf5bTxzuMu1tUM7T6gs3X7UfA",
        "owner_type": "unknown"
      },
      "to": {
        "address": "bc1qc2lr4szkceulnx7dcxu5rc683a287ln7teazv8",
        "owner_type": "unknown"
      },
      "timestamp": 1601541534,
      "amount": 53.42728,
      "amount_usd": 583651.56,
      "transaction_count": 1
    },
    {
      "blockchain": "bitcoin",
      "symbol": "btc",
      "id": "1001779384",
      "transaction_type": "transfer",
      "hash": "62b33f3316e9ce83aa9d1be3781e8ab159483d01027a98e4d086dca70e62e3f7",
      "from": {
        "address": "bc1qc2lr4szkceulnx7dcxu5rc683a287ln7teazv8",
        "owner_type": "unknown"
      },
      "to": {
        "address": "3MFt4VB9U52M85FzowCPieZfC2aGnU9z3W",
        "owner_type": "unknown"
      },
      "timestamp": 1601541534,
      "amount": 53.407402,
      "amount_usd": 583434.44,
      "transaction_count": 1
    },
    {
      "blockchain": "bitcoin",
      "symbol": "btc",
      "id": "1001779388",
      "transaction_type": "transfer",
      "hash": "312529497ef0e1e970516b096c4594493a696a71c5f6c66ddaa81626c1ae735c",
      "from": {
        "address": "39k9nXA2mCpFMzcyRZeH6QQT4tp9yod8vU",
        "owner_type": "unknown"
      },
      "to": {
        "address": "3Je2FWRDB5q9eGhpuVMW7pMVnDpfx8ZbHE",
        "owner_type": "unknown"
      },
      "timestamp": 1601541534,
      "amount": 79.80556,
      "amount_usd": 871813.75,
      "transaction_count": 1
    },
    {
      "blockchain": "bitcoin",
      "symbol": "btc",
      "id": "1001779390",
      "transaction_type": "transfer",
      "hash": "2ca2278ca93ceda88c525ddd15debfae151c06f9575d204dc299b9a15dddb089",
      "from": {
        "address": "3Je2FWRDB5q9eGhpuVMW7pMVnDpfx8ZbHE",
        "owner_type": "unknown"
      },
      "to": {
        "address": "33FA1AYEXskbynwVfUvthsunjFdRBTod89",
        "owner_type": "unknown"
      },
      "timestamp": 1601541534,
      "amount": 79.78365,
      "amount_usd": 871574.44,
      "transaction_count": 1
    },
    {
      "blockchain": "bitcoin",
      "symbol": "btc",
      "id": "1001779550",
      "transaction_type": "transfer",
      "hash": "02110b587bdef80d6b7a37853608b135bf0ab72b4031282cd09be354c4c3f5f8",
      "from": {
        "address": "3MFt4VB9U52M85FzowCPieZfC2aGnU9z3W",
        "owner_type": "unknown"
      },
      "to": {
        "address": "3JUxFLVZPWxM6WkoUgnS9QpjeNQmM1DaUv",
        "owner_type": "unknown"
      },
      "timestamp": 1601541534,
      "amount": 53.384193,
      "amount_usd": 583180.9,
      "transaction_count": 1
    },
    {
      "blockchain": "bitcoin",
      "symbol": "btc",
      "id": "1001779934",
      "transaction_type": "transfer",
      "hash": "371a81dafef101200595120995350dbf01be21e58343d4e15cdf72b898148bd8",
      "from": {
        "address": "bc1q2m0tyhzjclzs0j4g29xekhqc9c5t55h0p208gkjhrpgjzyt6zdtqmw2dus",
        "owner": "unknown owner 4",
        "owner_type": "unknown"
      },
      "to": {
        "address": "bc1qpx855dhcd7x34qns72j0dx7sctwklzsj0xn57r56ty72flv3gjzsttmd6j",
        "owner_type": "unknown"
      },
      "timestamp": 1601541534,
      "amount": 357.16168,
      "amount_usd": 3901714,
      "transaction_count": 1
    },
    {
      "blockchain": "bitcoin",
      "symbol": "btc",
      "id": "1001780038",
      "transaction_type": "transfer",
      "hash": "133c1175d2cdcd82eb30b5f320e9c96bbaf81c9c6f42927b80c251e9ef6461d7",
      "from": {
        "address": "156STn4i6yLrAMDp4LAYAKrLn3iovCQuRZ",
        "owner": "coinbase",
        "owner_type": "exchange"
      },
      "to": {
        "address": "1M6nQpDitpCfNF8UHME6sUAuCaCDaWaaxu",
        "owner": "coinbase",
        "owner_type": "exchange"
      },
      "timestamp": 1601541534,
      "amount": 68.05681,
      "amount_usd": 743467.8,
      "transaction_count": 1
    },
    {
      "blockchain": "bitcoin",
      "symbol": "btc",
      "id": "1001780119",
      "transaction_type": "transfer",
      "hash": "59629379fe577e104894ca7adad442f79359ae9d5874b3666a3183aa9b8a23a7",
      "from": {
        "address": "bc1qsd6pq2f89ztyd8vmejp47wux0qyuwxdusnl36hm3fy0sjc9kzpps4259g3",
        "owner_type": "unknown"
      },
      "to": {
        "address": "bc1qs5sxtkvxrppw6nytw3cmksstfac68eryxwgwutnlgcmlapk6065qek80ha",
        "owner_type": "unknown"
      },
      "timestamp": 1601541534,
      "amount": 343.25027,
      "amount_usd": 3749742.8,
      "transaction_count": 1
    },
    {
      "blockchain": "bitcoin",
      "symbol": "btc",
      "id": "1001780301",
      "transaction_type": "transfer",
      "hash": "e7244dcaabc87cc5b7a5c2945840363e63a240d31a2ca4ef5a0f72399396fd40",
      "from": {
        "address": "bc1q6c3d0etdnq2tvjz7knl0qg9hstywxdt0ma9th34gevq3xt3g3k3qldkqkk",
        "owner": "unknown owner 4",
        "owner_type": "unknown"
      },
      "to": {
        "address": "bc1qwgrw96xn4m5p5j5rtdrg3wghmfr7zh90qsp80594lyle32wru57quu7hd4",
        "owner_type": "unknown"
      },
      "timestamp": 1601541534,
      "amount": 359.70822,
      "amount_usd": 3929533,
      "transaction_count": 1
    },
    {
      "blockchain": "ethereum",
      "symbol": "usdt",
      "id": "1001784185",
      "transaction_type": "transfer",
      "hash": "4a09d4387060dfb37ebd5f6b242dff400d8f690f652a593bbc69ee2c6b2c5459",
      "from": {
        "address": "3dfd23a6c5e8bbcfc9581d2e864a68feb6a076d3",
        "owner": "aave lending pool",
        "owner_type": "other"
      },
      "to": {
        "address": "ee2826453a4fd5afeb7ceffeef3ffa2320081268",
        "owner_type": "unknown"
      },
      "timestamp": 1601541587,
      "amount": 500000,
      "amount_usd": 501923.9,
      "transaction_count": 1
    },
    {
      "blockchain": "ethereum",
      "symbol": "usdt",
      "id": "1001784194",
      "transaction_type": "transfer",
      "hash": "e15d73f111589f5c63ef50bde1f84d3ddf4074a81eccc56ef57daf159cb3e784",
      "from": {
        "address": "2ec2fba3b4ccebf2bef3cb02e4f64fc8b331d75b",
        "owner_type": "unknown"
      },
      "to": {
        "address": "ab5c66752a9e8167967685f1450532fb96d5d24f",
        "owner": "huobi",
        "owner_type": "exchange"
      },
      "timestamp": 1601541587,
      "amount": 512512.12,
      "amount_usd": 514484.16,
      "transaction_count": 1
    },
    {
      "blockchain": "ethereum",
      "symbol": "usdt",
      "id": "1001784717",
      "transaction_type": "transfer",
      "hash": "c9a727548ffe8bf033c2a06f43c8480f46b28723a08ab398186f7054adff3fe0",
      "from": {
        "address": "052b31e0f7fee490784bc01cd710a27bab363386",
        "owner_type": "unknown"
      },
      "to": {
        "address": "16219c410099c7f832429c0060126bc23f2feee4",
        "owner_type": "unknown"
      },
      "timestamp": 1601541602,
      "amount": 700000,
      "amount_usd": 702693.44,
      "transaction_count": 1
    },
    {
      "blockchain": "ethereum",
      "symbol": "usdt",
      "id": "1001785386",
      "transaction_type": "transfer",
      "hash": "bad5fe3a8e4ec2a3875086fa37d615a46397abb88ab5d470c52298f89478a6b9",
      "from": {
        "address": "6df27665d9d36abefc924fe4d22ba6065bf97587",
        "owner_type": "unknown"
      },
      "to": {
        "address": "29fce383c67d00954ac9367f6d3c8215989244ee",
        "owner_type": "unknown"
      },
      "timestamp": 1601541636,
      "amount": 550001,
      "amount_usd": 549865.94,
      "transaction_count": 1
    },
    {
      "blockchain": "ethereum",
      "symbol": "usdt",
      "id": "1001786348",
      "transaction_type": "transfer",
      "hash": "776731d8fdf68835c6229f4ed267ae75c166fe4ad7b04e402f489339edf41d85",
      "from": {
        "address": "e93381fb4c4f14bda253907b18fad305d799241a",
        "owner": "huobi",
        "owner_type": "exchange"
      },
      "to": {
        "address": "0ac551d1f16cc03ff67162bad02ed02d63117d79",
        "owner_type": "unknown"
      },
      "timestamp": 1601541683,
      "amount": 690000,
      "amount_usd": 694117.1,
      "transaction_count": 1
    },
    {
      "blockchain": "ethereum",
      "symbol": "usdt",
      "id": "1001786375",
      "transaction_type": "transfer",
      "hash": "f886b555317cedcc6b5e86ca5b5cf1dbb64c81768166679f033430aa32d5e19e",
      "from": {
        "address": "e81d6fce840ab873c7bccb6c2ab15e4b6daf92c7",
        "owner_type": "unknown"
      },
      "to": {
        "address": "6338320186cb6aaf110eb41b6192eaeb2704433c",
        "owner": "huobi",
        "owner_type": "exchange"
      },
      "timestamp": 1601541683,
      "amount": 500000,
      "amount_usd": 502983.4,
      "transaction_count": 1
    },
    {
      "blockchain": "ethereum",
      "symbol": "usdt",
      "id": "1001786857",
      "transaction_type": "transfer",
      "hash": "52c22f84db526ec5b18ac7cc508abe0e999b62fecb7c647e6892764b846310a7",
      "from": {
        "address": "052b31e0f7fee490784bc01cd710a27bab363386",
        "owner_type": "unknown"
      },
      "to": {
        "address": "69ee999d3b1580d30a871ea34864cce1ca664b25",
        "owner_type": "unknown"
      },
      "timestamp": 1601541689,
      "amount": 1000000,
      "amount_usd": 1001872.75,
      "transaction_count": 1
    },
    {
      "blockchain": "ethereum",
      "symbol": "usdt",
      "id": "1001787976",
      "transaction_type": "transfer",
      "hash": "60a3e7f613312496923104d8c8bbbcb41b6b2447d8444a71f00e9b3bd59d0c99",
      "from": {
        "address": "ee2826453a4fd5afeb7ceffeef3ffa2320081268",
        "owner_type": "unknown"
      },
      "to": {
        "address": "bef9124b9a1593982bb126bd97c1b8996caebade",
        "owner_type": "unknown"
      },
      "timestamp": 1601541765,
      "amount": 500000,
      "amount_usd": 501765.6,
      "transaction_count": 1
    },
    {
      "blockchain": "tron",
      "symbol": "usdt",
      "id": "1001785893",
      "transaction_type": "transfer",
      "hash": "cd0ae216a0bd1c17a0cd377455d42a3b378e287b3e581fa8908b0838f59a8c16",
      "from": {
        "address": "TNaRAoLUyYEV2uF7GUrzSjRQTU8v5ZJ5VR",
        "owner": "huobi",
        "owner_type": "exchange"
      },
      "to": {
        "address": "TLYCdaoumqmMpKByyv6ci1eZi3G2dbtZ7o",
        "owner_type": "unknown"
      },
      "timestamp": 1601541843,
      "amount": 600000,
      "amount_usd": 599852.6,
      "transaction_count": 1
    },
    {
      "blockchain": "ethereum",
      "symbol": "usdt",
      "id": "1001791187",
      "transaction_type": "transfer",
      "hash": "f75cd1e6cd6245e449339067b57be37be4cfff2e7a425806367117b99d3567cb",
      "from": {
        "address": "0681d8db095565fe8a346fa0277bffde9c0edbbf",
        "owner": "binance",
        "owner_type": "exchange"
      },
      "to": {
        "address": "c9a3396d80ee390da944c19be2091500c32071a2",
        "owner": "huobi",
        "owner_type": "exchange"
      },
      "timestamp": 1601541899,
      "amount": 2249996,
      "amount_usd": 2246760.8,
      "transaction_count": 1
    },
    {
      "blockchain": "ethereum",
      "symbol": "usdt",
      "id": "1001794298",
      "transaction_type": "transfer",
      "hash": "19a5a23ae11590e4a40458030fb1fbd0ffb0c9b77eef2a4a3066b4b60afad699",
      "from": {
        "address": "6338320186cb6aaf110eb41b6192eaeb2704433c",
        "owner": "huobi",
        "owner_type": "exchange"
      },
      "to": {
        "address": "0a98fb70939162725ae66e626fe4b52cff62c2e5",
        "owner": "huobi",
        "owner_type": "exchange"
      },
      "timestamp": 1601542103,
      "amount": 500000,
      "amount_usd": 502371.4,
      "transaction_count": 1
    },
    {
      "blockchain": "ethereum",
      "symbol": "usdc",
      "id": "1001794893",
      "transaction_type": "transfer",
      "hash": "8094789ba83f6825163b9fe95a17a55eae0b032cd84cf437832358217f7aa63d",
      "from": {
        "address": "3f5ce5fbfe3e9af3971dd833d26ba9b5c936f0be",
        "owner": "binance",
        "owner_type": "exchange"
      },
      "to": {
        "address": "0681d8db095565fe8a346fa0277bffde9c0edbbf",
        "owner": "binance",
        "owner_type": "exchange"
      },
      "timestamp": 1601542146,
      "amount": 3887080,
      "amount_usd": 3887080,
      "transaction_count": 1
    },
    {
      "blockchain": "ethereum",
      "symbol": "usdt",
      "id": "1001794949",
      "transaction_type": "transfer",
      "hash": "47d9bbb5c3cda5c1807e51e755796c91b1ca1b035d77ccac4bc25dcd6dc2b71f",
      "from": {
        "address": "3f5ce5fbfe3e9af3971dd833d26ba9b5c936f0be",
        "owner": "binance",
        "owner_type": "exchange"
      },
      "to": {
        "address": "0681d8db095565fe8a346fa0277bffde9c0edbbf",
        "owner": "binance",
        "owner_type": "exchange"
      },
      "timestamp": 1601542146,
      "amount": 10328565,
      "amount_usd": 10377552,
      "transaction_count": 1
    },
    {
      "blockchain": "ethereum",
      "symbol": "usdt",
      "id": "1001796277",
      "transaction_type": "transfer",
      "hash": "dc540e0ec8ccd988eae2283c1b182623013dda6f2dca41459e7222c564179938",
      "from": {
        "address": "343d44192ec0c87a8aee8fe45e7419ec27dfac05",
        "owner_type": "unknown"
      },
      "to": {
        "address": "cc9e5f4c34747be66a25ee0fb72fc3ea25721601",
        "owner_type": "unknown"
      },
      "timestamp": 1601542203,
      "amount": 629673,
      "amount_usd": 632591.8,
      "transaction_count": 1
    },
    {
      "blockchain": "ethereum",
      "symbol": "eth",
      "id": "1001809127",
      "transaction_type": "transfer",
      "hash": "f514c2896c91008d2e2fda2d7a2a4aec99b6d55b4cd886a3253a64457d0d8254",
      "from": {
        "address": "4faa508925950a7291c91fbfe0ffd495acfdd86f",
        "owner_type": "unknown"
      },
      "to": {
        "address": "c02aaa39b223fe8d0a0e5c4f27ead9083c756cc2",
        "owner": "wrapped ether",
        "owner_type": "other"
      },
      "timestamp": 1601542284,
      "amount": 1369.5,
      "amount_usd": 504363.66,
      "transaction_count": 1
    },
    {
      "blockchain": "ethereum",
      "symbol": "pax",
      "id": "1001809252",
      "transaction_type": "transfer",
      "hash": "e8ef6f8e2193eac0c3db93df48f905b498a73bf54b9f0c367a913414f0a8f625",
      "from": {
        "address": "c5a8859c44ac8aa2169afacf45b87c08593bec10",
        "owner_type": "unknown"
      },
      "to": {
        "address": "8025504c05b146ae25a84c82a73f447a88b8ae9a",
        "owner_type": "unknown"
      },
      "timestamp": 1601542284,
      "amount": 1699995,
      "amount_usd": 1704876.1,
      "transaction_count": 1
    },
    {
      "blockchain": "ethereum",
      "symbol": "busd",
      "id": "1001809257",
      "transaction_type": "transfer",
      "hash": "dc00c1194849e4e8a322473fc8c85b1dc9e8f7b51bf400d2431d4ca392047e57",
      "from": {
        "address": "c5a8859c44ac8aa2169afacf45b87c08593bec10",
        "owner_type": "unknown"
      },
      "to": {
        "address": "f2103b01cd7957f3a9d9726bbb74c0ccd3f355d3",
        "owner": "binance",
        "owner_type": "exchange"
      },
      "timestamp": 1601542284,
      "amount": 1002000,
      "amount_usd": 1002000,
      "transaction_count": 1
    },
    {
      "blockchain": "tron",
      "symbol": "usdt",
      "id": "1001794597",
      "transaction_type": "transfer",
      "hash": "69d51a0aa7c3d4b2010484caf9d460f22d48e5ad37ffcd0b3480629d061637c4",
      "from": {
        "address": "TVAqsT3AjsKd2XuP2W4C94V1smq9TxfZZ9",
        "owner_type": "unknown"
      },
      "to": {
        "address": "TSaJqQ1AZ2bEYyqBwBmJqCBSPv8KPRTAdv",
        "owner_type": "unknown"
      },
      "timestamp": 1601542302,
      "amount": 2000000,
      "amount_usd": 2009485.6,
      "transaction_count": 1
    },
    {
      "blockchain": "ethereum",
      "symbol": "eth",
      "id": "1001809446",
      "transaction_type": "transfer",
      "hash": "e43f4057407f0be9501d9041079c4dfc1b807f1d1bfaae59d20d5200ef22c3a7",
      "from": {
        "address": "b1e60dd62c5e6d04f4fa01e962ce2c2065be8808",
        "owner_type": "unknown"
      },
      "to": {
        "address": "5b990c664ae7e759763acfec76e11c289c53be77",
        "owner_type": "unknown"
      },
      "timestamp": 1601542326,
      "amount": 2618.66,
      "amount_usd": 964408.1,
      "transaction_count": 1
    },
    {
      "blockchain": "bitcoin",
      "symbol": "btc",
      "id": "1001797364",
      "transaction_type": "transfer",
      "hash": "938df849b2e32e15c0047224868240cd97c04d9777a8e6c3d92dd5d816f29808",
      "from": {
        "address": "Multiple Addresses",
        "owner_type": "unknown"
      },
      "to": {
        "address": "bc1qtnpgchrry6a59xtkpxj7k5vw0dcmq0ywej3ka9vnqcg6t8m4qc7sra4v9d",
        "owner_type": "unknown"
      },
      "timestamp": 1601542345,
      "amount": 85.232285,
      "amount_usd": 931726.5,
      "transaction_count": 1
    },
    {
      "blockchain": "bitcoin",
      "symbol": "btc",
      "id": "1001797365",
      "transaction_type": "transfer",
      "hash": "938df849b2e32e15c0047224868240cd97c04d9777a8e6c3d92dd5d816f29808",
      "from": {
        "address": "Multiple Addresses",
        "owner_type": "unknown"
      },
      "to": {
        "address": "bc1qdtms6d0ywzxng2r7tur7c6fukg3t57ndfp0vvfmcknuyzpk2rv7s99eny4",
        "owner_type": "unknown"
      },
      "timestamp": 1601542345,
      "amount": 85.23158,
      "amount_usd": 931718.8,
      "transaction_count": 1
    },
    {
      "blockchain": "bitcoin",
      "symbol": "btc",
      "id": "1001797604",
      "transaction_type": "transfer",
      "hash": "21cd0eda2fde7e1261d0551291d11530e1daaf17e91f97ce20870cb479f00804",
      "from": {
        "address": "Multiple Addresses",
        "owner": "okex",
        "owner_type": "exchange"
      },
      "to": {
        "address": "bc1qxznhl9v0tpqcdkd6e2df86vkw4ec934hvzljlwmzpetevsg9a39sdjwcgl",
        "owner": "okex",
        "owner_type": "exchange"
      },
      "timestamp": 1601542345,
      "amount": 143.34235,
      "amount_usd": 1566963.2,
      "transaction_count": 1
    },
    {
      "blockchain": "bitcoin",
      "symbol": "btc",
      "id": "1001797605",
      "transaction_type": "transfer",
      "hash": "21cd0eda2fde7e1261d0551291d11530e1daaf17e91f97ce20870cb479f00804",
      "from": {
        "address": "Multiple Addresses",
        "owner": "okex",
        "owner_type": "exchange"
      },
      "to": {
        "address": "3E2adcep2NRRpriLnWn1AvW3AHKqBx2mMr",
        "owner": "unknown owner 4",
        "owner_type": "unknown"
      },
      "timestamp": 1601542345,
      "amount": 80,
      "amount_usd": 874529.1,
      "transaction_count": 1
    },
    {
      "blockchain": "bitcoin",
      "symbol": "btc",
      "id": "1001797839",
      "transaction_type": "transfer",
      "hash": "b6ac8d32126371bdfe85045c0886e18b30f028903baaf6b9f6888b1de7551186",
      "from": {
        "address": "33zU1yGK8DGfp4aprxHDAxZUzw1ULtrEtx",
        "owner_type": "unknown"
      },
      "to": {
        "address": "3JMy3NhTCpBUag4swoMzG1GgbCPL8QEmQu",
        "owner_type": "unknown"
      },
      "timestamp": 1601542345,
      "amount": 456.01013,
      "amount_usd": 4984927,
      "transaction_count": 1
    },
    {
      "blockchain": "bitcoin",
      "symbol": "btc",
      "id": "1001797840",
      "transaction_type": "transfer",
      "hash": "b6ac8d32126371bdfe85045c0886e18b30f028903baaf6b9f6888b1de7551186",
      "from": {
        "address": "33zU1yGK8DGfp4aprxHDAxZUzw1ULtrEtx",
        "owner_type": "unknown"
      },
      "to": {
        "address": "3JcsCDePGX85cLS9vAYTCCn9ZLPpQZueWu",
        "owner": "okex",
        "owner_type": "exchange"
      },
      "timestamp": 1601542345,
      "amount": 150,
      "amount_usd": 1639742.1,
      "transaction_count": 1
    },
    {
      "blockchain": "bitcoin",
      "symbol": "btc",
      "id": "1001797853",
      "transaction_type": "transfer",
      "hash": "cad0d23ac3c87477a23c5333ce27f9536d1d14f79169dca2df212970a715a580",
      "from": {
        "address": "1NDyJtNTjmwk5xPNhjgAMu4HDHigtobu1s",
        "owner": "binance",
        "owner_type": "exchange"
      },
      "to": {
        "address": "37p3PS1hKqzYhiVswbqN6nxbwyUoTZvf1E",
        "owner": "coinbase",
        "owner_type": "exchange"
      },
      "timestamp": 1601542345,
      "amount": 279.9996,
      "amount_usd": 3060847.8,
      "transaction_count": 1
    },
    {
      "blockchain": "bitcoin",
      "symbol": "btc",
      "id": "1001797854",
      "transaction_type": "transfer",
      "hash": "cad0d23ac3c87477a23c5333ce27f9536d1d14f79169dca2df212970a715a580",
      "from": {
        "address": "1NDyJtNTjmwk5xPNhjgAMu4HDHigtobu1s",
        "owner": "binance",
        "owner_type": "exchange"
      },
      "to": {
        "address": "152AtBDiFmw5UpCxr8mh3gx9PMex6LgdT1",
        "owner_type": "unknown"
      },
      "timestamp": 1601542345,
      "amount": 99.9996,
      "amount_usd": 1093157.1,
      "transaction_count": 1
    },
    {
      "blockchain": "bitcoin",
      "symbol": "btc",
      "id": "1001797921",
      "transaction_type": "transfer",
      "hash": "98f1af4babb5f15a2fa6e6a0ffd5e4238bcaf1680c09a2cf3ea8052a9949d4d6",
      "from": {
        "address": "Multiple Addresses",
        "owner": "binance",
        "owner_type": "exchange"
      },
      "to": {
        "address": "1NBSAB1xtgN5BUbUJJtoe8ejySzmqwBjHG",
        "owner": "okex",
        "owner_type": "exchange"
      },
      "timestamp": 1601542345,
      "amount": 49.9996,
      "amount_usd": 546576.4,
      "transaction_count": 1
    },
    {
      "blockchain": "bitcoin",
      "symbol": "btc",
      "id": "1001798377",
      "transaction_type": "transfer",
      "hash": "49428e18b7814da3cd9039025b6cfdb8e6d035092541af6130a1be73b086bbed",
      "from": {
        "address": "Multiple Addresses",
        "owner_type": "unknown"
      },
      "to": {
        "address": "38HXrasJovQu7AZUBRTctWzGr2xahQFwmS",
        "owner": "bitstamp",
        "owner_type": "exchange"
      },
      "timestamp": 1601542345,
      "amount": 120.9995,
      "amount_usd": 1322719.9,
      "transaction_count": 1
    },
    {
      "blockchain": "bitcoin",
      "symbol": "btc",
      "id": "1001798669",
      "transaction_type": "transfer",
      "hash": "5152ea9935b4b39aeb7db0187b91469f872104479484b61ef31f6aca5d599c72",
      "from": {
        "address": "1PCkFoQZMqcuRubfwbnP4Zhid9GDfvEKM8",
        "owner": "coinbase",
        "owner_type": "exchange"
      },
      "to": {
        "address": "3AgC4WA7YwecRPgUZ4qnWDr9E1iZZzh1Ws",
        "owner_type": "unknown"
      },
      "timestamp": 1601542345,
      "amount": 69.655655,
      "amount_usd": 761448.75,
      "transaction_count": 1
    },
    {
      "blockchain": "bitcoin",
      "symbol": "btc",
      "id": "1001799446",
      "transaction_type": "transfer",
      "hash": "960dfdcc73436ef6f51916286158e35fc0f57d06775b0c83fc4ad499276427da",
      "from": {
        "address": "Multiple Addresses",
        "owner_type": "unknown"
      },
      "to": {
        "address": "32HXrDZnCMDThQFELLXMa8sSzLYe9FupbB",
        "owner_type": "unknown"
      },
      "timestamp": 1601542345,
      "amount": 87.39274,
      "amount_usd": 955343.7,
      "transaction_count": 1
    },
    {
      "blockchain": "bitcoin",
      "symbol": "btc",
      "id": "1001799509",
      "transaction_type": "transfer",
      "hash": "bd9025c0842c48682f9677073536be986c3e636dd83ec6d8e095a53c69beaa4f",
      "from": {
        "address": "bc1qk4kq8tsf5ezd9js72xfcp7qrqeg0002leu79zcjt24449yn860dqcfml45",
        "owner_type": "unknown"
      },
      "to": {
        "address": "bc1qlp6s9dras0zdmtcqwqn3h58msvt7sjwtn3k96e6zw3syzfe6wcdq7gh4k5",
        "owner_type": "unknown"
      },
      "timestamp": 1601542345,
      "amount": 127.9665,
      "amount_usd": 1398880.4,
      "transaction_count": 1
    },
    {
      "blockchain": "bitcoin",
      "symbol": "btc",
      "id": "1001801202",
      "transaction_type": "transfer",
      "hash": "ba6e4de07502b8a4f487b5a18b3cee335e3d22933a0900110873aaa00e93dd38",
      "from": {
        "address": "37p3PS1hKqzYhiVswbqN6nxbwyUoTZvf1E",
        "owner": "coinbase",
        "owner_type": "exchange"
      },
      "to": {
        "address": "1NBSAB1xtgN5BUbUJJtoe8ejySzmqwBjHG",
        "owner": "okex",
        "owner_type": "exchange"
      },
      "timestamp": 1601542345,
      "amount": 49.999973,
      "amount_usd": 546580.44,
      "transaction_count": 1
    },
    {
      "blockchain": "bitcoin",
      "symbol": "btc",
      "id": "1001801389",
      "transaction_type": "transfer",
      "hash": "d25332763a4997d12f00570d8b83fd15e5730b5ab7e22d01ae6f82af2cd571c0",
      "from": {
        "address": "Multiple Addresses",
        "owner_type": "unknown"
      },
      "to": {
        "address": "37taR4aoC1nAZm2TvYpPU6ewPPRbEygawL",
        "owner_type": "unknown"
      },
      "timestamp": 1601542345,
      "amount": 121,
      "amount_usd": 1322725.4,
      "transaction_count": 1
    },
    {
      "blockchain": "bitcoin",
      "symbol": "btc",
      "id": "1001801660",
      "transaction_type": "transfer",
      "hash": "810ca451f784c8dbaf52bd12db7d79006aa0e6127a3ab97c85f541c2548f1d4a",
      "from": {
        "address": "3JUxFLVZPWxM6WkoUgnS9QpjeNQmM1DaUv",
        "owner_type": "unknown"
      },
      "to": {
        "address": "3NqrwjpEQqi2yryDrVGzKJnqyrZbBY5w8T",
        "owner_type": "unknown"
      },
      "timestamp": 1601542345,
      "amount": 53.36642,
      "amount_usd": 583381.1,
      "transaction_count": 1
    },
    {
      "blockchain": "bitcoin",
      "symbol": "btc",
      "id": "1001808125",
      "transaction_type": "transfer",
      "hash": "c595f1e63121c24e0585de552aefe0e6f66d4b179d6af6cc3de88f94f358ec15",
      "from": {
        "address": "1KXXjKxWpZnCSmVD18CzFAJJ31Qrn7r7LV",
        "owner_type": "unknown"
      },
      "to": {
        "address": "1PKdt4ZkBexW4yos7X5zsXKCjW6FEdrAaF",
        "owner_type": "unknown"
      },
      "timestamp": 1601542345,
      "amount": 142.99706,
      "amount_usd": 1563188.6,
      "transaction_count": 1
    },
    {
      "blockchain": "bitcoin",
      "symbol": "btc",
      "id": "1001808243",
      "transaction_type": "transfer",
      "hash": "96bc3eec9012de81ff634ea6e7441f535b7d48b31a8fa90d6389d6bd67c08d2b",
      "from": {
        "address": "17YB4VbGs9Js6uKXbWiL8pvDZ7vh7aNfaJ",
        "owner_type": "unknown"
      },
      "to": {
        "address": "3LKvBTMW2noxS7pMqDFwVCQXvWbMsdNmfz",
        "owner": "unknown owner 24",
        "owner_type": "unknown"
      },
      "timestamp": 1601542345,
      "amount": 100.01619,
      "amount_usd": 1093338.4,
      "transaction_count": 1
    },
    {
      "blockchain": "ethereum",
      "symbol": "pax",
      "id": "1001810187",
      "transaction_type": "transfer",
      "hash": "2838fa4dc7d784d3109e5ca483438f399c2c20baf6536a7cec141b1cb7ccd8e4",
      "from": {
        "address": "8025504c05b146ae25a84c82a73f447a88b8ae9a",
        "owner_type": "unknown"
      },
      "to": {
        "address": "2faf487a4414fe77e2327f0bf4ae2a264a776ad2",
        "owner": "ftx",
        "owner_type": "exchange"
      },
      "timestamp": 1601542374,
      "amount": 1699995,
      "amount_usd": 1704876.1,
      "transaction_count": 1
    },
    {
      "blockchain": "ethereum",
      "symbol": "usdt",
      "id": "1001810413",
      "transaction_type": "transfer",
      "hash": "655e8d053bfb97bc66c7adcc9c3d612aae14d364b14036581a8a099972648371",
      "from": {
        "address": "c9a3396d80ee390da944c19be2091500c32071a2",
        "owner": "huobi",
        "owner_type": "exchange"
      },
      "to": {
        "address": "46705dfff24256421a05d056c29e81bdc09723b8",
        "owner": "huobi",
        "owner_type": "exchange"
      },
      "timestamp": 1601542376,
      "amount": 2249996,
      "amount_usd": 2258113.2,
      "transaction_count": 1
    },
    {
      "blockchain": "ethereum",
      "symbol": "usdt",
      "id": "1001812150",
      "transaction_type": "transfer",
      "hash": "aae38305268f816498ec3d4c864354156311d3cff0cf8e0f43deea25f5898ada",
      "from": {
        "address": "2890dd19637f45e9b8f2485ad760ec1c7c42b551",
        "owner_type": "unknown"
      },
      "to": {
        "address": "fab8432bf61ef8274e9d0b9e94335941177ccdff",
        "owner_type": "unknown"
      },
      "timestamp": 1601542461,
      "amount": 550000,
      "amount_usd": 549010.9,
      "transaction_count": 1
    }
  ]
}